{
  "diseases": {
    "diabetes": ["diabetes", "diabete", "diabetes mellitus", "açúcar no sangue", "glicemia alta"],
    "hipertensão": ["hipertensão", "pressão alta", "pressão arterial alta", "hipertensao"],
    "câncer": ["câncer", "cancer", "tumor", "neoplasia", "oncologia", "carcinoma"],
    "depressão": ["depressão", "depressao", "transtorno depressivo", "tristeza crônica"],
    "ansiedade": ["ansiedade", "transtorno de ansiedade", "nervosismo", "angústia"],
    "asma": ["asma", "bronquite asmática", "broncoespasmo"],
    "artrite": ["artrite", "artrose", "osteoartrite", "dor nas juntas", "reumatismo"],
    "alzheimer": ["alzheimer", "doença de alzheimer", "demência", "perda de memória"],
    "parkinson": ["parkinson", "doença de parkinson", "tremor", "mal de parkinson"],
    "epilepsia": ["epilepsia", "convulsão", "crise convulsiva", "ataque epiléptico"],
    "obesidade": ["obesidade", "excesso de peso", "sobrepeso", "gordo"],
    "covid-19": ["covid-19", "covid", "coronavírus", "sars-cov-2", "pandemia"],
    "infarto": ["infarto", "ataque cardíaco", "infarto do miocárdio", "ataque do coração"],
    "avc": ["avc", "derrame", "acidente vascular cerebral", "isquemia cerebral"],
    "pneumonia": ["pneumonia", "infecção pulmonar", "pulmão infectado"],
    "tuberculose": ["tuberculose", "tb", "tuberculose pulmonar"],
    "dengue": ["dengue", "febre dengue", "mosquito da dengue"],
    "malária": ["malária", "malaria", "febre terçã", "paludismo"],
    "hepatite": ["hepatite", "hepatite viral", "inflamação do fígado"],
    "hiv": ["hiv", "aids", "vírus da imunodeficiência"],
    "insuficiência renal": ["insuficiência renal", "doença renal", "rim", "diálise"],
    "insuficiência cardíaca": ["insuficiência cardíaca", "coração fraco", "falência cardíaca"],
    "esclerose múltipla": ["esclerose múltipla", "em", "esclerose"],
    "lúpus": ["lúpus", "lupus", "doença autoimune"],
    "psoríase": ["psoríase", "psoriase", "doença de pele"],
    "esquizofrenia": ["esquizofrenia", "psicose", "transtorno psicótico"],
    "bipolar": ["bipolar", "transtorno bipolar", "maníaco-depressivo"],
    "tdah": ["tdah", "déficit de atenção", "hiperatividade"],
    "fibromialgia": ["fibromialgia", "dor crônica", "síndrome fibromiálgica"],
    "enxaqueca": ["enxaqueca", "migranea", "dor de cabeça forte"]
  },
  "drugs": {
    "paracetamol": ["paracetamol", "acetaminofeno", "tylenol"],
    "ibuprofeno": ["ibuprofeno", "advil", "motrin", "alivium"],
    "aspirina": ["aspirina", "ácido acetilsalicílico", "aas"],
    "metformina": ["metformina", "glifage", "glucoformin"],
    "losartana": ["losartana", "losartan", "cozaar"],
    "omeprazol": ["omeprazol", "prilosec", "losec"],
    "amoxicilina": ["amoxicilina", "amoxil", "novamox"],
    "azitromicina": ["azitromicina", "zitromax", "azitro"],
    "dipirona": ["dipirona", "metamizol", "novalgina"],
    "diclofenaco": ["diclofenaco", "voltaren", "cataflan"],
    "atorvastatina": ["atorvastatina", "lipitor", "citalor"],
    "sinvastatina": ["sinvastatina", "zocor", "sinvastacor"],
    "cloroquina": ["cloroquina", "hidroxicloroquina", "reuquinol"],
    "ivermectina": ["ivermectina", "revectina", "vermectil"],
    "prednisona": ["prednisona", "meticorten", "prednisolona"],
    "dexametasona": ["dexametasona", "decadron", "corticoide"],
    "insulina": ["insulina", "novolin", "humalog", "lantus"],
    "enalapril": ["enalapril", "renitec", "vasopril"],
    "captopril": ["captopril", "capoten"],
    "fluoxetina": ["fluoxetina", "prozac", "daforin"],
    "sertralina": ["sertralina", "zoloft", "tolrest"],
    "clonazepam": ["clonazepam", "rivotril", "clonotril"],
    "alprazolam": ["alprazolam", "frontal", "xanax"],
    "risperidona": ["risperidona", "risperdal", "respidon"],
    "carbamazepina": ["carbamazepina", "tegretol", "tegretard"]
  },
  "therapeutic_classes": {
    "antibióticos": ["antibiótico", "antibiotico", "antimicrobiano", "bactericida"],
    "antivirais": ["antiviral", "antivírus"],
    "antifúngicos": ["antifúngico", "antifungico", "antimicótico"],
    "analgésicos": ["analgésico", "analgesico", "para dor", "alívio da dor"],
    "anti-inflamatórios": ["anti-inflamatório", "antiinflamatorio", "inflamação"],
    "antidepressivos": ["antidepressivo", "para depressão"],
    "ansiolíticos": ["ansiolítico", "calmante", "tranquilizante"],
    "antipsicóticos": ["antipsicótico", "neuroléptico"],
    "anticonvulsivantes": ["anticonvulsivante", "antiepiléptico"],
    "anti-hipertensivos": ["anti-hipertensivo", "para pressão", "hipotensor"],
    "diuréticos": ["diurético", "para retenção de líquido"],
    "hipoglicemiantes": ["hipoglicemiante", "antidiabético", "para diabetes"],
    "estatinas": ["estatina", "para colesterol", "hipolipemiante"],
    "corticosteroides": ["corticosteroide", "corticoide", "cortisona"],
    "imunossupressores": ["imunossupressor", "imunomodulador"]
  },
  "general_terms": {
    "tratamento": ["tratamento", "terapia", "cura", "medicação"],
    "efeito colateral": ["efeito colateral", "efeito adverso", "reação adversa"],
    "dosagem": ["dosagem", "dose", "posologia"],
    "indicação": ["indicação", "uso", "prescrito para"],
    "contraindicação": ["contraindicação", "não usar", "evitar"],
    "interação medicamentosa": ["interação medicamentosa", "interação com outros remédios"],
    "genérico": ["genérico", "medicamento genérico", "similar"],
    "bula": ["bula", "informações do medicamento"],
    "anvisa": ["anvisa", "agência nacional de vigilância sanitária", "registro"],
    "sus": ["sus", "sistema único de saúde", "saúde pública"]
  }
}
